mcmodupdater/__init__.py
mcmodupdater/cli.py
mcmodupdater/executorThreadsHandler.py
mcmodupdater/futures_features.py
mcmodupdater/hashing.py
mcmodupdater/main.py
mcmodupdater/models.py
mcmodupdater/pathclass.py
mcmodupdater/requests_handler.py
mcmodupdater/utils.py
mcmodupdater/version.py
mcmodupdater/writer.py
mcmodupdater-0.1.2.dist-info/LICENSE
mcmodupdater-0.1.2.dist-info/METADATA
mcmodupdater-0.1.2.dist-info/WHEEL
mcmodupdater-0.1.2.dist-info/entry_points.txt
mcmodupdater-0.1.2.dist-info/RECORD
