Metadata-Version: 2.3
Name: mcmodupdater
Version: 0.1.2
Summary: 
License: MIT
Author: kurotom
Author-email: 55354389+kurotom@users.noreply.github.com
Requires-Python: >=3.9
Classifier: Operating System :: OS Independent
Classifier: Programming Language :: Python :: 3.9
Classifier: Programming Language :: Python :: 3.10
Classifier: Programming Language :: Python :: 3.11
Classifier: Programming Language :: Python :: 3.12
Requires-Dist: mmh2 (>=0.1.0,<0.2.0)
Requires-Dist: platformdirs (>=4.3.8,<5.0.0)
Requires-Dist: requests (>=2.32.5,<3.0.0)
